pythaiid/__init__.py
pythaiid/__main__.py
pythaiid/thaiid.py
pythaiid-0.1.0.dist-info/LICENSE
pythaiid-0.1.0.dist-info/METADATA
pythaiid-0.1.0.dist-info/WHEEL
pythaiid-0.1.0.dist-info/entry_points.txt
pythaiid-0.1.0.dist-info/top_level.txt
pythaiid-0.1.0.dist-info/RECORD
