Metadata-Version: 2.1
Name: pythaiid
Version: 0.1.0
Summary: Verify and random Thai Nationality ID
Home-page: https://github.com/jojoee/pythaiid
Author: Nathachai Thongniran
Author-email: inid3a@gmail.com
License: MIT
Platform: UNKNOWN
Classifier: License :: OSI Approved :: MIT License
Classifier: Programming Language :: Python :: 3
Classifier: Programming Language :: Python :: 3.7
License-File: LICENSE
